[[{"location":"E:\\android workspace-gameAD201506\\gad2\\Pintu","type":"PROJECT","hints":{"PROJECT_NAME":"Pintu"}},"ABSENT"],[{"location":"E:\\android workspace-gameAD201506\\gad2\\gamead_IM2\\libs\\BmobSDK_V3.3.2_0128.jar","type":"JAR","hints":{}},"ABSENT"],[{"location":"F:\\adt-bundle-windows-x86_64-20131030\\sdk\\platforms\\android-19\\android.jar","type":"JAR","hints":{}},"com.google.android:android:4.4.0"],[{"location":"E:\\android workspace-gameAD201506\\gad2\\gamead_IM2","type":"PROJECT","hints":{"PROJECT_NAME":"gamead_IM2"}},"ABSENT"]]